azure/confidentialledger/__init__.py
azure/confidentialledger/_client.py
azure/confidentialledger/_configuration.py
azure/confidentialledger/_patch.py
azure/confidentialledger/_serialization.py
azure/confidentialledger/_vendor.py
azure/confidentialledger/_version.py
azure/confidentialledger/py.typed
azure/confidentialledger/_operations/__init__.py
azure/confidentialledger/_operations/_operations.py
azure/confidentialledger/_operations/_patch.py
azure/confidentialledger/aio/__init__.py
azure/confidentialledger/aio/_client.py
azure/confidentialledger/aio/_configuration.py
azure/confidentialledger/aio/_patch.py
azure/confidentialledger/aio/_vendor.py
azure/confidentialledger/aio/_operations/__init__.py
azure/confidentialledger/aio/_operations/_operations.py
azure/confidentialledger/aio/_operations/_patch.py
azure/confidentialledger/certificate/__init__.py
azure/confidentialledger/certificate/_client.py
azure/confidentialledger/certificate/_configuration.py
azure/confidentialledger/certificate/_patch.py
azure/confidentialledger/certificate/_serialization.py
azure/confidentialledger/certificate/_vendor.py
azure/confidentialledger/certificate/_operations/__init__.py
azure/confidentialledger/certificate/_operations/_operations.py
azure/confidentialledger/certificate/_operations/_patch.py
azure/confidentialledger/certificate/aio/__init__.py
azure/confidentialledger/certificate/aio/_client.py
azure/confidentialledger/certificate/aio/_configuration.py
azure/confidentialledger/certificate/aio/_patch.py
azure/confidentialledger/certificate/aio/_vendor.py
azure/confidentialledger/certificate/aio/_operations/__init__.py
azure/confidentialledger/certificate/aio/_operations/_operations.py
azure/confidentialledger/certificate/aio/_operations/_patch.py
azure/confidentialledger/receipt/__init__.py
azure/confidentialledger/receipt/_claims_digest_computation.py
azure/confidentialledger/receipt/_claims_models.py
azure/confidentialledger/receipt/_receipt_models.py
azure_confidentialledger-1.1.1.dist-info/LICENSE
azure_confidentialledger-1.1.1.dist-info/METADATA
azure_confidentialledger-1.1.1.dist-info/WHEEL
azure_confidentialledger-1.1.1.dist-info/top_level.txt
azure_confidentialledger-1.1.1.dist-info/RECORD
